app/__init__.py
app/agent_registry.py
app/agent_tools.py
app/agent_watcher.py
app/create_agent.py
app/toolkit.py
app/toolkit_client.py
app/agent_templates/__init__.py
app/agent_templates/weather_agent_template.py
app/agents/__init__.py
app/agents/deploy_template_agent.py
app/agents/stock_lookup_agent.py
app/tools/__init__.py
app/tools/brave_search.py
app/tools/browser_automation.py
app/tools/document_management.py
app/tools/excel.py
app/tools/filesystem.py
app/tools/fred.py
app/tools/news_api.py
app/tools/ppt.py
app/tools/sequential_thinking.py
app/tools/shopify.py
app/tools/streamlit.py
app/tools/time_tools.py
app/tools/worldbank.py
app/tools/yfinance.py
mcptoolkit-1.0.3.dist-info/LICENSE
mcptoolkit-1.0.3.dist-info/METADATA
mcptoolkit-1.0.3.dist-info/WHEEL
mcptoolkit-1.0.3.dist-info/entry_points.txt
mcptoolkit-1.0.3.dist-info/top_level.txt
mcptoolkit-1.0.3.dist-info/RECORD
