Metadata-Version: 2.2
Name: mcptoolkit
Version: 1.0.3
Summary: A modular server implementation for Claude AI assistants with integrated tools
Home-page: https://github.com/getfounded/mcp-tool-kit
Author: getfounded
Author-email: jack@pivotplanpro.com
Classifier: Programming Language :: Python :: 3
Classifier: Programming Language :: Python :: 3.9
Classifier: Programming Language :: Python :: 3.10
Classifier: Programming Language :: Python :: 3.11
Classifier: Programming Language :: Python :: 3.12
Classifier: License :: OSI Approved :: MIT License
Classifier: Operating System :: OS Independent
Classifier: Development Status :: 4 - Beta
Classifier: Intended Audience :: Developers
Classifier: Topic :: Software Development :: Libraries :: Python Modules
Requires-Python: >=3.9
License-File: LICENSE
Requires-Dist: mcp>=0.4.1
Requires-Dist: newsapi-python>=0.2.7
Requires-Dist: python-dotenv>=1.0.1
Requires-Dist: httpx>=0.27.0
Requires-Dist: pillow>=10.2.0
Requires-Dist: pydantic>=2.7.3
Requires-Dist: pandas>=2.2.1
Requires-Dist: requests>=2.32.3
Requires-Dist: python-pptx>=0.6.22
Requires-Dist: nltk>=3.8.1
Requires-Dist: msal>=1.28.0
Requires-Dist: psutil>=5.9.8
Requires-Dist: simple_salesforce>=1.12.5
Requires-Dist: seaborn>=0.13.2
Requires-Dist: matplotlib>=3.8.4
Requires-Dist: pdf2image>=1.17.0
Requires-Dist: PyPDF2>=3.0.1
Requires-Dist: pytesseract>=0.3.10
Requires-Dist: aiohttp>=3.9.5
Requires-Dist: playwright>=1.43.1
Requires-Dist: yfinance>=0.2.42
Requires-Dist: fredapi>=0.5.1
Requires-Dist: streamlit>=1.32.2
Requires-Dist: pyyaml>=6.0.1
Requires-Dist: azure-cli>=2.57.0
Requires-Dist: setuptools>=69.2.0
Requires-Dist: uvicorn>=0.34.0
Requires-Dist: watchdog>=3.0.0
Requires-Dist: reportlab>=3.6.15
Requires-Dist: scipy>=1.12.2
Requires-Dist: scikit-learn>=1.3.2
Requires-Dist: fastapi>=0.106.0
Dynamic: author
Dynamic: author-email
Dynamic: classifier
Dynamic: description
Dynamic: description-content-type
Dynamic: home-page
Dynamic: requires-dist
Dynamic: requires-python
Dynamic: summary
